sphinx_automodapi/__init__.py
sphinx_automodapi/autodoc_enhancements.py
sphinx_automodapi/automodapi.py
sphinx_automodapi/automodsumm.py
sphinx_automodapi/smart_resolver.py
sphinx_automodapi/utils.py
sphinx_automodapi/version.py
sphinx_automodapi/templates/autosummary_core/base.rst
sphinx_automodapi/templates/autosummary_core/class.rst
sphinx_automodapi/templates/autosummary_core/module.rst
sphinx_automodapi/tests/__init__.py
sphinx_automodapi/tests/helpers.py
sphinx_automodapi/tests/test_autodoc_enhancements.py
sphinx_automodapi/tests/test_automodapi.py
sphinx_automodapi/tests/test_automodsumm.py
sphinx_automodapi/tests/test_cases.py
sphinx_automodapi/tests/test_utils.py
sphinx_automodapi/tests/cases/abstract_classes/README.md
sphinx_automodapi/tests/cases/abstract_classes/input/index.rst
sphinx_automodapi/tests/cases/abstract_classes/output_prop_is_attr/index.rst.automodapi
sphinx_automodapi/tests/cases/abstract_classes/output_prop_is_attr/index.rst.automodsumm
sphinx_automodapi/tests/cases/abstract_classes/output_prop_is_attr/api/sphinx_automodapi.tests.example_module.abstract_classes.SequenceSubclass.rst
sphinx_automodapi/tests/cases/abstract_classes/output_prop_is_not_attr/index.rst.automodapi
sphinx_automodapi/tests/cases/abstract_classes/output_prop_is_not_attr/index.rst.automodsumm
sphinx_automodapi/tests/cases/abstract_classes/output_prop_is_not_attr/api/sphinx_automodapi.tests.example_module.abstract_classes.SequenceSubclass.rst
sphinx_automodapi/tests/cases/allowed_names/README.md
sphinx_automodapi/tests/cases/allowed_names/input/index.rst
sphinx_automodapi/tests/cases/allowed_names/output_prop_is_attr/index.rst.automodapi
sphinx_automodapi/tests/cases/allowed_names/output_prop_is_attr/index.rst.automodsumm
sphinx_automodapi/tests/cases/allowed_names/output_prop_is_attr/api/sphinx_automodapi.tests.example_module.Egg.rst
sphinx_automodapi/tests/cases/allowed_names/output_prop_is_attr/api/sphinx_automodapi.tests.example_module.Spam.rst
sphinx_automodapi-0.22.0.dist-info/licenses/LICENSE.rst
sphinx_automodapi-0.22.0.dist-info/METADATA
sphinx_automodapi-0.22.0.dist-info/WHEEL
sphinx_automodapi-0.22.0.dist-info/top_level.txt
sphinx_automodapi-0.22.0.dist-info/RECORD
