Metadata-Version: 2.4
Name: sphinx-automodapi
Version: 0.22.0
Summary: Sphinx extension for auto-generating API documentation for entire modules
Home-page: https://github.com/astropy/sphinx-automodapi
Author: The Astropy Developers
Author-email: astropy.team@gmail.com
License: BSD-3-Clause
Classifier: Development Status :: 5 - Production/Stable
Classifier: Intended Audience :: Developers
Classifier: Programming Language :: Python
Classifier: Programming Language :: Python :: 3
Classifier: Operating System :: OS Independent
Requires-Python: >=3.10
License-File: LICENSE.rst
Requires-Dist: packaging
Requires-Dist: sphinx>=5
Provides-Extra: test
Requires-Dist: pytest; extra == "test"
Requires-Dist: pytest-cov; extra == "test"
Requires-Dist: cython; extra == "test"
Requires-Dist: coverage; extra == "test"
Requires-Dist: setuptools; python_version >= "3.12" and extra == "test"
Provides-Extra: rtd
Requires-Dist: sphinx-rtd-theme; extra == "rtd"
Dynamic: license-file
